aruco_markers/__init__.py
aruco_markers/calibrate.py
aruco_markers/camera.py
aruco_markers/detect.py
aruco_markers/main.py
aruco_markers/marker.py
aruco_markers/utils.py
aruco_markers-1.1.6.dist-info/LICENSE
aruco_markers-1.1.6.dist-info/METADATA
aruco_markers-1.1.6.dist-info/WHEEL
aruco_markers-1.1.6.dist-info/entry_points.txt
aruco_markers-1.1.6.dist-info/top_level.txt
aruco_markers-1.1.6.dist-info/RECORD
