Metadata-Version: 2.1
Name: aruco-markers
Version: 1.1.6
Summary:  A compact Python package for handling ArUCo markers.
Home-page: https://github.com/cmower/aruco_markers
Author: Christopher E. Mower
Author-email: "Christopher E. Mower" <christopher.mower@kcl.ac.uk>
License: Apache License 2.0
Project-URL: Homepage, https://cmower.github.io/aruco_markers/
Project-URL: Documentation, https://cmower.github.io/aruco_markers/
Project-URL: Bug Tracker, https://github.com/cmower/aruco_markers/issues
Project-URL: Source, https://github.com/cmower/aruco_markers
Classifier: Programming Language :: Python :: 3
Classifier: License :: OSI Approved :: GNU Lesser General Public License v3 or later (LGPLv3+)
Classifier: Operating System :: OS Independent
Requires-Python: >=3.7
License-File: LICENSE
